pymagi.py
pymagi-0.0.4.dist-info/LICENSE
pymagi-0.0.4.dist-info/METADATA
pymagi-0.0.4.dist-info/WHEEL
pymagi-0.0.4.dist-info/top_level.txt
pymagi-0.0.4.dist-info/RECORD
