Metadata-Version: 2.1
Name: pymagi
Version: 0.0.4
Summary: A python based client for CyberChef API server.
Home-page: https://github.com/kabilan1290/pymagi
Author: Game0v3r
Author-email: tamiltuts1290@gmail.com
License: UNKNOWN
Keywords: cyberchef,ctf tool,ctf toolkit,decoder
Platform: UNKNOWN
Classifier: Development Status :: 3 - Alpha
Classifier: Intended Audience :: Developers
Classifier: License :: OSI Approved :: MIT License
Classifier: Operating System :: OS Independent
Classifier: Programming Language :: Python :: 3
Requires-Python: >3
License-File: LICENSE
